MANIFEST
MANIFEST.in
README.rst
requirements.txt
setup.py
test-requirements.txt
examples/config0-simple-sources-list.yml
examples/config1-overwrite-source-handler-watcher.yml
examples/config2-yet-another-sources-format.yml
examples/config3-custom-pipe.yml
examples/config4-custom-pipe-with-options.yml
logdog/__init__.py
logdog/__init__.pyc
logdog/app.py
logdog/app.pyc
logdog/cli.py
logdog/cli.pyc
logdog/compat.py
logdog/compat.pyc
logdog/default_config.py
logdog/default_config.pyc
logdog/version.py
logdog/version.pyc
logdog.egg-info/PKG-INFO
logdog.egg-info/SOURCES.txt
logdog.egg-info/dependency_links.txt
logdog.egg-info/requires.txt
logdog.egg-info/top_level.txt
logdog/core/__init__.py
logdog/core/__init__.pyc
logdog/core/base_role.py
logdog/core/base_role.pyc
logdog/core/config.py
logdog/core/config.pyc
logdog/core/log.py
logdog/core/log.pyc
logdog/core/msg.py
logdog/core/msg.pyc
logdog/core/path.py
logdog/core/path.pyc
logdog/core/policies.py
logdog/core/policies.pyc
logdog/core/register.py
logdog/core/register.pyc
logdog/core/utils/__init__.py
logdog/core/utils/__init__.pyc
logdog/core/utils/six.py
logdog/core/utils/six.pyc
logdog/roles/__init__.py
logdog/roles/__init__.pyc
logdog/roles/collectors/__init__.py
logdog/roles/collectors/base.py
logdog/roles/connectors/__init__.py
logdog/roles/connectors/__init__.pyc
logdog/roles/connectors/base.py
logdog/roles/connectors/base.pyc
logdog/roles/connectors/zmq_tunnel.py
logdog/roles/connectors/zmq_tunnel.pyc
logdog/roles/formatters/__init__.py
logdog/roles/formatters/__init__.pyc
logdog/roles/formatters/base.py
logdog/roles/formatters/base.pyc
logdog/roles/formatters/fmtr.py
logdog/roles/formatters/fmtr.pyc
logdog/roles/forwarders/__init__.py
logdog/roles/forwarders/base.py
logdog/roles/forwarders/broadcast.py
logdog/roles/forwarders/round_robin.py
logdog/roles/parsers/__init__.py
logdog/roles/parsers/__init__.pyc
logdog/roles/parsers/base.py
logdog/roles/parsers/base.pyc
logdog/roles/parsers/regex.py
logdog/roles/parsers/regex.pyc
logdog/roles/pipes/__init__.py
logdog/roles/pipes/__init__.pyc
logdog/roles/pipes/base.py
logdog/roles/pipes/base.pyc
