Metadata-Version: 1.0
Name: logdog
Version: 0.2.11
Summary: logs watching + webui
Home-page: https://github.com/miphreal/python-logdog/
Author: Evgeny Lychkovsky
Author-email: miphreal@gamil.com
License: UNKNOWN
Platform: UNKNOWN
